winfetch/__init__.py
winfetch/__main__.py
winfetch-1.0.4.dist-info/LICENSE
winfetch-1.0.4.dist-info/METADATA
winfetch-1.0.4.dist-info/WHEEL
winfetch-1.0.4.dist-info/entry_points.txt
winfetch-1.0.4.dist-info/top_level.txt
winfetch-1.0.4.dist-info/RECORD
