Metadata-Version: 2.1
Name: winfetch
Version: 1.0.4
Summary: command: winfetch. i made this as a funny windows version of neofetch in like an hour.
Author: gamerjamer43
Author-email: gamerjamer43@protonmail.com
License: GNU GENERAL PUBLIC LICENSE V3
Platform: windows
License-File: LICENSE
